XgridFoundation/__init__.py
XgridFoundation/_metadata.py
pyobjc_framework_XgridFoundation-6.2.2.dist-info/LICENSE.txt
pyobjc_framework_XgridFoundation-6.2.2.dist-info/METADATA
pyobjc_framework_XgridFoundation-6.2.2.dist-info/WHEEL
pyobjc_framework_XgridFoundation-6.2.2.dist-info/top_level.txt
pyobjc_framework_XgridFoundation-6.2.2.dist-info/RECORD
