Metadata-Version: 2.1
Name: pyobjc-framework-XgridFoundation
Version: 6.2.2
Summary: Wrappers for the framework XgridFoundation on macOS
Home-page: https://github.com/ronaldoussoren/pyobjc
Author: Ronald Oussoren
Author-email: pyobjc-dev@lists.sourceforge.net
License: MIT License
Keywords: PyObjC,XgridFoundation
Platform: MacOS X (<=10.7)
Classifier: Development Status :: 5 - Production/Stable
Classifier: Environment :: Console
Classifier: Environment :: MacOS X :: Cocoa
Classifier: Intended Audience :: Developers
Classifier: License :: OSI Approved :: MIT License
Classifier: Natural Language :: English
Classifier: Operating System :: MacOS :: MacOS X
Classifier: Programming Language :: Python
Classifier: Programming Language :: Python :: 3
Classifier: Programming Language :: Python :: 3.6
Classifier: Programming Language :: Python :: 3.7
Classifier: Programming Language :: Python :: 3.8
Classifier: Programming Language :: Python :: 3.9
Classifier: Programming Language :: Python :: Implementation :: CPython
Classifier: Programming Language :: Objective C
Classifier: Topic :: Software Development :: Libraries :: Python Modules
Classifier: Topic :: Software Development :: User Interfaces
Requires-Python: >=3.6
Project-URL: Documentation, https://pyobjc.readthedocs.io/en/latest/
Project-URL: Issue tracker, https://github.com/ronaldoussoren/pyobjc/issues
Project-URL: Repository, https://github.com/ronaldoussoren/pyobjc
Requires-Dist: pyobjc-core (>=6.2.2)
Requires-Dist: pyobjc-framework-Cocoa (>=6.2.2)
